tubelearns/__init__.py
tubelearns/install_models.py
tubelearns/sourcing.py
tubelearns/tokenizers.py
tubelearns-2.1.0.dist-info/LICENSE
tubelearns-2.1.0.dist-info/METADATA
tubelearns-2.1.0.dist-info/WHEEL
tubelearns-2.1.0.dist-info/entry_points.txt
tubelearns-2.1.0.dist-info/top_level.txt
tubelearns-2.1.0.dist-info/RECORD
