Metadata-Version: 2.1
Name: tubelearns
Version: 2.1.0
Summary: Python script for extracting, cleaning, and tokenizing YouTube video transcripts for Pre-Processing in machine learning.
Home-page: UNKNOWN
Author: KabilPreethamK
Author-email: <kabilpreethamk@gmail.com>
License: UNKNOWN
Keywords: python,video,transcript,raw data,cleaning,machine learning,pre-processing
Platform: UNKNOWN
Classifier: Development Status :: 5 - Production/Stable
Classifier: Intended Audience :: Developers
Classifier: Intended Audience :: Education
Classifier: Intended Audience :: Science/Research
Classifier: License :: OSI Approved :: MIT License
Classifier: Programming Language :: Python :: 3
Classifier: Operating System :: Unix
Classifier: Operating System :: MacOS :: MacOS X
Classifier: Operating System :: Microsoft :: Windows
Classifier: Operating System :: POSIX :: Linux
License-File: LICENSE
Requires-Dist: num2words
Requires-Dist: pytube
Requires-Dist: regex
Requires-Dist: requests
Requires-Dist: spacy
Requires-Dist: youtube-transcript-api
